{
    "sin": [
        "123456789",
        "123 456 789",
        "123-456-789"
    ],
    "date": "2025-Nov-12",
    "name": "John Smith",
    "phone": "123-456-7789",
    "signature": "JSmith",
    "spouse_sin": [
        "456789012",
        "456 789 012",
        "456-789-012"
    ],
    "spouse_date": "2025-Nov-12",
    "spouse_name": "Maria Smith",
    "spouse_phone": "234-567-8890",
    "spouse_oas_gis": 0,
    "explain_changes": "Began looking for work",
    "checkbox_work_no": "unselected",
    "spouse_signature": "MSmith",
    "applicant_oas_gis": 0,
    "checkbox_moved_no": "selected",
    "checkbox_work_yes": "selected",
    "checkbox_moved_yes": "unselected",
    "checkbox_school_no": "selected",
    "checkbox_school_yes": "unselected",
    "checkbox_shelter_no": "selected",
    "checkbox_warrant_no": "selected",
    "spouse_trust_income": 0,
    "checkbox_shelter_yes": "unselected",
    "checkbox_warrant_yes": "unselected",
    "spouse_child_support": 0,
    "spouse_rental_income": 0,
    "applicant_trust_income": 0,
    "checkbox_dependants_no": "selected",
    "applicant_child_support": 0,
    "applicant_rental_income": 0,
    "checkbox_dependants_yes": "unselected",
    "checkbox_work_spouse_no": "selected",
    "checkbox_moved_spouse_no": "selected",
    "checkbox_work_spouse_yes": "unselected",
    "spouse_income_tax_refund": 0,
    "spouse_room_board_income": 0,
    "checkbox_family_assets_no": "selected",
    "checkbox_moved_spouse_yes": "unselected",
    "checkbox_school_spouse_no": "selected",
    "spouse_child_tax_benefits": 0,
    "checkbox_family_assets_yes": "unselected",
    "checkbox_school_spouse_yes": "unselected",
    "checkbox_warrant_spouse_no": "selected",
    "applicant_income_tax_refund": 0,
    "applicant_room_board_income": 0,
    "checkbox_need_assistance_no": "unselected",
    "checkbox_warrant_spouse_yes": "unselected",
    "spouse_employment_insurance": 0,
    "spouse_workers_compensation": 0,
    "applicant_child_tax_benefits": 0,
    "checkbox_need_assistance_yes": "selected",
    "spouse_net_employment_income": 0,
    "spouse_tax_credits_gst_credit": 0,
    "applicant_employment_insurance": 0,
    "applicant_workers_compensation": 0,
    "checkbox_employment_changes_no": "selected",
    "spouse_canada_pension_plan_cpp": 0,
    "spouse_spousal_support_alimony": 0,
    "applicant_net_employment_income": 0,
    "checkbox_employment_changes_yes": "unselected",
    "spouse_workbc_financial_support": 0,
    "applicant_tax_credits_gst_credit": 0,
    "applicant_canada_pension_plan_cpp": 0,
    "applicant_spousal_support_alimony": 0,
    "applicant_workbc_financial_support": 0,
    "spouse_other_income_money_received": 0,
    "applicant_other_income_money_received": 0,
    "checkbox_employment_changes_spouse_no": "selected",
    "applicant_income_of_dependent_children": 0,
    "checkbox_employment_changes_spouse_yes": "unselected",
    "spouse_student_funding_loans_bursaries": 0,
    "applicant_student_funding_loans_bursaries": 0,
    "spouse_private_pensions_retirement_disability": 0,
    "applicant_private_pensions_retirement_disability": 0
}
